portex/__init__.py
portex/__version__.py
portex-0.0.1.dist-info/LICENSE
portex-0.0.1.dist-info/METADATA
portex-0.0.1.dist-info/WHEEL
portex-0.0.1.dist-info/top_level.txt
portex-0.0.1.dist-info/RECORD
