Metadata-Version: 2.1
Name: portex
Version: 0.0.1
Summary: Portex Python Package
Home-page: https://github.com/Project-OpenBytes/portex
Author: Graviti
Author-email: pypi@graviti.com
License: Apache License 2.0
Keywords: portex,schema,openbytes
Platform: UNKNOWN
Classifier: Development Status :: 1 - Planning
Classifier: License :: OSI Approved :: Apache Software License
Classifier: Operating System :: OS Independent
Classifier: Programming Language :: Python
Classifier: Programming Language :: Python :: 3
Classifier: Programming Language :: Python :: 3 :: Only
